[{"Date":"02/02/2024","Opponent":"Southern Wesleyan","Result":"W 9-5"},{"Date":"02/03/2024(1)","Opponent":"Southern Wesleyan","Result":"L 4-5 (12)"},{"Date":"02/03/2024(2)","Opponent":"Southern Wesleyan","Result":"W 12-2"},{"Date":"02/07/2024","Opponent":"Lincoln Memorial","Result":"W 6-4"},{"Date":"02/09/2024","Opponent":"Mars Hill","Result":"W 18-4"},{"Date":"02/10/2024","Opponent":"Mars Hill","Result":"L 4-5"},{"Date":"02/11/2024","Opponent":"Mars Hill","Result":"W 10-9"},{"Date":"02/13/2024","Opponent":"Young Harris","Result":"L 7-9"},{"Date":"02/16/2024","Opponent":"@ Shorter","Result":"W 10-3"},{"Date":"02/17/2024(1)","Opponent":"@ Shorter","Result":"L 4-6"},{"Date":"02/17/2024(2)","Opponent":"@ Shorter","Result":"W 12-3"},{"Date":"02/20/2024","Opponent":"Carson-Newman","Result":"W 9-4"},{"Date":"02/23/2024","Opponent":"Valdosta St.","Result":"W 18-4"},{"Date":"02/24/2024(1)","Opponent":"Valdosta St.","Result":"W 10-5"},{"Date":"02/24/2024(2)","Opponent":"Valdosta St.","Result":"L 1-8"},{"Date":"03/02/2024","Opponent":"@ West Ga.","Result":"W 10-8"},{"Date":"03/03/2024(1)","Opponent":"@ West Ga.","Result":"W 6-1"},{"Date":"03/03/2024(2)","Opponent":"@ West Ga.","Result":"L 1-2"},{"Date":"03/06/2024","Opponent":"@ Lincoln Memorial","Result":"L 12-16"},{"Date":"03/09/2024","Opponent":"Cedarville","Result":"W 13-3"},{"Date":"03/10/2024(1)","Opponent":"Cedarville","Result":"W 20-10"},{"Date":"03/10/2024(2)","Opponent":"Cedarville","Result":"W 8-1"},{"Date":"03/12/2024","Opponent":"@ Carson-Newman","Result":"W 3-1"},{"Date":"03/16/2024(1)","Opponent":"AUM","Result":"W 7-1"},{"Date":"03/16/2024(2)","Opponent":"AUM","Result":"W 4-3"},{"Date":"03/17/2024","Opponent":"AUM","Result":"L 2-8"},{"Date":"03/19/2024","Opponent":"North Georgia","Result":"W 15-5"},{"Date":"03/23/2024(1)","Opponent":"Christian Brothers","Result":"W 19-9"},{"Date":"03/23/2024(2)","Opponent":"Christian Brothers","Result":"W 28-10"},{"Date":"03/24/2024","Opponent":"Christian Brothers","Result":"W 9-3"},{"Date":"03/27/2024","Opponent":"@ Tusculum","Result":"L 4-6"},{"Date":"03/29/2024","Opponent":"@ Alabama Huntsville","Result":"W 13-3"},{"Date":"03/30/2024(1)","Opponent":"@ Alabama Huntsville","Result":"W 15-8"},{"Date":"03/30/2024(2)","Opponent":"@ Alabama Huntsville","Result":"W 11-8 (9)"},{"Date":"04/03/2024","Opponent":"Trevecca Nazarene","Result":"W 14-4"},{"Date":"04/05/2024","Opponent":"West Ala.","Result":"W 16-0"},{"Date":"04/06/2024(1)","Opponent":"West Ala.","Result":"W 13-3"},{"Date":"04/06/2024(2)","Opponent":"West Ala.","Result":"L 3-10"},{"Date":"04/10/2024","Opponent":"Tusculum","Result":"W 10-5"},{"Date":"04/12/2024","Opponent":"@ Union (TN)","Result":"W 13-2"},{"Date":"04/13/2024(1)","Opponent":"@ Union (TN)","Result":"W 7-6"},{"Date":"04/13/2024(2)","Opponent":"@ Union (TN)","Result":"L 6-7"},{"Date":"04/16/2024","Opponent":"@ North Georgia","Result":"L 2-21"},{"Date":"04/19/2024","Opponent":"Delta St.","Result":"W 9-6"},{"Date":"04/20/2024(1)","Opponent":"Delta St.","Result":"W 17-2"},{"Date":"04/20/2024(2)","Opponent":"Delta St.","Result":"W 6-5"},{"Date":"04/23/2024","Opponent":"@ Young Harris","Result":"L 2-14"},{"Date":"04/26/2024","Opponent":"@ West Florida","Result":"W 7-3"},{"Date":"04/27/2024(1)","Opponent":"@ West Florida","Result":"L 2-5"},{"Date":"04/27/2024(2)","Opponent":"@ West Florida","Result":"W 2-0"},{"Date":"05/03/2024","Opponent":"West Ga. @Oxford, AL","Result":"W 10-2"},{"Date":"05/04/2024","Opponent":"Valdosta St. @Oxford, AL","Result":"L 0-10"},{"Date":"05/05/2024","Opponent":"Delta St. @Oxford, AL","Result":"L 3-5"},{"Date":"05/16/2024","Opponent":"#5 AUM @Tampa, FL (2024 NCAA Division II Baseball Championship)","Result":"W 24-7"},{"Date":"05/17/2024","Opponent":"@#2 Tampa 2024 NCAA Division II Baseball Championship","Result":"L 1-13"},{"Date":"05/18/2024","Opponent":"@#2 Tampa 2024 NCAA Division II Baseball Championship","Result":"L 3-16"},{"Date":"05/18/2024","Opponent":"#5 AUM @Tampa, FL (2024 NCAA Division II Baseball Championship)","Result":"W 8-7"}]
