[{"Date":"02/02/2024","Opponent":"@ Embry-Riddle (FL)","Result":"L 3-6"},{"Date":"02/03/2024(1)","Opponent":"@ Rollins","Result":"L 4-6"},{"Date":"02/03/2024(2)","Opponent":"@ Rollins","Result":"L 3-12"},{"Date":"02/06/2024","Opponent":"@ Spring Hill","Result":"W 14-12 (10)"},{"Date":"02/09/2024(1)","Opponent":"UVA Wise","Result":"W 5-3"},{"Date":"02/09/2024(2)","Opponent":"UVA Wise","Result":"W 9-3"},{"Date":"02/10/2024","Opponent":"UVA Wise","Result":"W 15-7"},{"Date":"02/14/2024","Opponent":"@ West Ala.","Result":"W 12-0"},{"Date":"02/16/2024","Opponent":"Northwood","Result":"W 4-3"},{"Date":"02/17/2024","Opponent":"Northwood","Result":"W 11-5"},{"Date":"02/18/2024","Opponent":"Northwood","Result":"W 8-3"},{"Date":"02/23/2024","Opponent":"Christian Brothers","Result":"L 4-17"},{"Date":"02/24/2024(1)","Opponent":"Christian Brothers","Result":"W 16-4"},{"Date":"02/24/2024(2)","Opponent":"Christian Brothers","Result":"W 9-2"},{"Date":"02/27/2024","Opponent":"Ga. Southwestern","Result":"L 2-10"},{"Date":"03/01/2024","Opponent":"@ Delta St.","Result":"L 2-8"},{"Date":"03/02/2024(1)","Opponent":"@ Delta St.","Result":"W 2-0"},{"Date":"03/02/2024(2)","Opponent":"@ Delta St.","Result":"L 10-14"},{"Date":"03/06/2024","Opponent":"@ Columbus St.","Result":"L 7-8"},{"Date":"03/09/2024(1)","Opponent":"West Ga.","Result":"W 10-8"},{"Date":"03/09/2024(2)","Opponent":"West Ga.","Result":"L 4-11"},{"Date":"03/10/2024","Opponent":"West Ga.","Result":"W 22-6"},{"Date":"03/12/2024","Opponent":"Spring Hill","Result":"L 3-4"},{"Date":"03/16/2024(1)","Opponent":"@ Mississippi Col.","Result":"W 8-5"},{"Date":"03/16/2024(2)","Opponent":"@ Mississippi Col.","Result":"W 8-0"},{"Date":"03/17/2024","Opponent":"@ Mississippi Col.","Result":"W 10-8"},{"Date":"03/20/2024","Opponent":"@ Miles","Result":"W 5-1"},{"Date":"03/23/2024(1)","Opponent":"@ Alabama Huntsville","Result":"W 9-6 (10)"},{"Date":"03/23/2024(2)","Opponent":"@ Alabama Huntsville","Result":"W 7-6 (8)"},{"Date":"03/24/2024","Opponent":"@ Alabama Huntsville","Result":"W 5-2"},{"Date":"03/27/2024(1)","Opponent":"@ Carson-Newman","Result":"L 5-6"},{"Date":"03/27/2024(2)","Opponent":"@ Carson-Newman","Result":"L 4-6"},{"Date":"03/29/2024","Opponent":"Valdosta St.","Result":"W 7-6"},{"Date":"03/30/2024(1)","Opponent":"Valdosta St.","Result":"L 11-12 (10)"},{"Date":"03/30/2024(2)","Opponent":"Valdosta St.","Result":"L 3-9"},{"Date":"04/05/2024","Opponent":"@ Shorter","Result":"L 6-13"},{"Date":"04/06/2024(1)","Opponent":"@ Shorter","Result":"L 2-9"},{"Date":"04/06/2024(2)","Opponent":"@ Shorter","Result":"L 5-6"},{"Date":"04/12/2024","Opponent":"West Florida","Result":"W 4-1"},{"Date":"04/13/2024(1)","Opponent":"West Florida","Result":"W 10-8"},{"Date":"04/13/2024(2)","Opponent":"West Florida","Result":"L 1-8"},{"Date":"04/16/2024","Opponent":"West Ala.","Result":"W 13-8"},{"Date":"04/19/2024","Opponent":"@ Union (TN)","Result":"L 1-2"},{"Date":"04/20/2024(1)","Opponent":"@ Union (TN)","Result":"W 8-3"},{"Date":"04/20/2024(2)","Opponent":"@ Union (TN)","Result":"L 1-4"},{"Date":"04/26/2024","Opponent":"AUM","Result":"W 9-3"},{"Date":"04/27/2024(1)","Opponent":"AUM","Result":"L 3-4"},{"Date":"04/27/2024(2)","Opponent":"AUM","Result":"W 4-1"},{"Date":"05/03/2024","Opponent":"Valdosta St. @Oxford, Ala.","Result":"L 2-13"},{"Date":"05/04/2024","Opponent":"West Ga. @Oxford, AL","Result":"W 5-1"},{"Date":"05/05/2024","Opponent":"AUM @Oxford, AL","Result":"W 7-5 (11)"},{"Date":"05/06/2024","Opponent":"West Florida @Oxford, AL","Result":"L 1-9"}]
