[{"Date":"02/03/2024(1)","Opponent":"Kentucky St.","Result":"L 2-18"},{"Date":"02/03/2024(2)","Opponent":"Kentucky St.","Result":"L 6-12"},{"Date":"02/04/2024","Opponent":"@ Kentucky St.","Result":"L 0-17"},{"Date":"02/06/2024(1)","Opponent":"@ Morris","Result":"W 8-4"},{"Date":"02/06/2024(2)","Opponent":"@ Morris","Result":"L 8-9"},{"Date":"02/09/2024","Opponent":"Lincoln (PA) @Peachtree City, GA","Result":"W 15-9"},{"Date":"02/10/2024","Opponent":"Southeastern Bapt. @Atlanta, Ga.","Result":"W 20-5"},{"Date":"02/10/2024","Opponent":"Wilberforce @Peachtree City, Ga.","Result":"W 15-5"},{"Date":"02/17/2024","Opponent":"Tuskegee","Result":"W 16-4"},{"Date":"02/18/2024(1)","Opponent":"Tuskegee","Result":"W 6-2"},{"Date":"02/18/2024(2)","Opponent":"Tuskegee","Result":"L 6-7"},{"Date":"02/24/2024","Opponent":"Spring Hill","Result":"L 3-7"},{"Date":"02/25/2024(1)","Opponent":"Spring Hill","Result":"L 3-4"},{"Date":"02/25/2024(2)","Opponent":"Spring Hill","Result":"L 6-13"},{"Date":"03/02/2024(1)","Opponent":"@ Miles","Result":"L 13-15"},{"Date":"03/02/2024(2)","Opponent":"@ Miles","Result":"L 2-3"},{"Date":"03/03/2024","Opponent":"@ Miles","Result":"L 2-7"},{"Date":"03/07/2024(1)","Opponent":"@ Edward Waters","Result":"L 3-9"},{"Date":"03/07/2024(2)","Opponent":"@ Edward Waters","Result":"W 16-6"},{"Date":"03/08/2024","Opponent":"@ Edward Waters","Result":"L 3-8"},{"Date":"03/13/2024","Opponent":"@ Paine","Result":"L 3-14"},{"Date":"03/16/2024","Opponent":"Savannah St.","Result":"L 2-12"},{"Date":"03/17/2024(1)","Opponent":"Savannah St.","Result":"W 8-6"},{"Date":"03/17/2024(2)","Opponent":"Savannah St.","Result":"L 5-14"},{"Date":"03/20/2024(1)","Opponent":"Morris","Result":"W 12-3"},{"Date":"03/20/2024(2)","Opponent":"Morris","Result":"W 12-0"},{"Date":"03/23/2024(1)","Opponent":"@ Kentucky St.","Result":"L 14-17"},{"Date":"03/23/2024(2)","Opponent":"@ Kentucky St.","Result":"L 3-8"},{"Date":"03/24/2024","Opponent":"@ Kentucky St.","Result":"W 13-3"},{"Date":"03/27/2024(1)","Opponent":"Paine","Result":"L 0-7"},{"Date":"03/27/2024(2)","Opponent":"Paine","Result":"L 2-8"},{"Date":"03/29/2024","Opponent":"Benedict","Result":"W 2-1"},{"Date":"03/30/2024(1)","Opponent":"Benedict","Result":"W 15-5"},{"Date":"03/30/2024(2)","Opponent":"Benedict","Result":"L 8-12"},{"Date":"04/05/2024","Opponent":"@ Albany St. (GA)","Result":"L 6-16"},{"Date":"04/06/2024","Opponent":"@ Albany St. (GA)","Result":"L 5-6"},{"Date":"04/06/2024(2)","Opponent":"@ Albany St. (GA)","Result":"L 5-19"},{"Date":"04/09/2024","Opponent":"@ Shorter","Result":"L 4-16"},{"Date":"04/13/2024(1)","Opponent":"@ Clark Atlanta","Result":"W 12-8"},{"Date":"04/13/2024(2)","Opponent":"@ Clark Atlanta","Result":"W 9-2"},{"Date":"04/14/2024","Opponent":"@ Clark Atlanta","Result":"W 15-0"},{"Date":"04/16/2024","Opponent":"@ Shorter","Result":"L 6-11"},{"Date":"04/20/2024(1)","Opponent":"Lane","Result":"W 7-4"},{"Date":"04/20/2024(2)","Opponent":"Lane","Result":"W 18-4"},{"Date":"04/21/2024","Opponent":"Lane","Result":"Ppd"},{"Date":"04/26/2024(1)","Opponent":"@ LeMoyne-Owen","Result":"W 20-5"},{"Date":"04/26/2024(2)","Opponent":"@ LeMoyne-Owen","Result":"W 22-16"},{"Date":"04/27/2024","Opponent":"@ LeMoyne-Owen","Result":"W 13-0"},{"Date":"05/02/2024","Opponent":"Spring Hill @Albany, GA","Result":"L 3-4 (12)"},{"Date":"05/03/2024","Opponent":"Lane @Albany, GA","Result":"L 4-7"}]
