[{"year":"2024","school":"Ky. Wesleyan","conference":"G-MAC","division":"2","Player":"Evan Oakley","Yr":"So","ERA":3.43,"W":3,"L":6,"App":13,"GS":13,"SHO":2,"IP":78.2,"H":66,"R":38,"ER":30,"RA/9":4.35,"BB":20,"BB%":6,"SO":88,"SO%":26.3,"BF":335,"AB":295,"2B-A":10,"3B-A":1,"HR-A":7,"Bk":0,"WP":2,"HB":15,"IBB":0,"SO_BB_Ratio":4.4,"BAA":0.224,"OBPA":0.305,"SLGA":0.336,"SHA":4,"SFA":1,"GO":60,"FO":76,"SV":0,"teamid":574409,"conference_id":"30182","player_id":"8263274","player_url":"http://stats.ncaa.org/players/8263274?year_stat_category_id=15081"},{"year":"2024","school":"Ky. Wesleyan","conference":"G-MAC","division":"2","Player":"Cade Moore","Yr":"Jr","ERA":9,"W":0,"L":0,"App":1,"GS":0,"SHO":0,"IP":1,"H":5,"R":5,"ER":1,"RA/9":45,"BB":0,"BB%":0,"SO":0,"SO%":0,"BF":8,"AB":8,"2B-A":0,"3B-A":0,"HR-A":2,"Bk":0,"WP":0,"HB":0,"IBB":0,"BAA":0.625,"OBPA":0.625,"SLGA":1.375,"SHA":0,"SFA":0,"GO":2,"FO":0,"SV":0,"teamid":574409,"conference_id":"30182","player_id":"8265898","player_url":"http://stats.ncaa.org/players/8265898?year_stat_category_id=15081"},{"year":"2024","school":"Ky. Wesleyan","conference":"G-MAC","division":"2","Player":"Sam McFarland","Yr":"So","ERA":5.91,"W":0,"L":0,"App":3,"GS":0,"SHO":0,"IP":10.2,"H":12,"R":10,"ER":7,"RA/9":8.44,"BB":3,"BB%":6.2,"SO":5,"SO%":10.4,"BF":48,"AB":42,"2B-A":1,"3B-A":2,"HR-A":2,"Bk":1,"WP":2,"HB":2,"IBB":0,"SO_BB_Ratio":1.67,"BAA":0.286,"OBPA":0.354,"SLGA":0.548,"SHA":0,"SFA":1,"GO":14,"FO":10,"SV":0,"teamid":574409,"conference_id":"30182","player_id":"8274279","player_url":"http://stats.ncaa.org/players/8274279?year_stat_category_id=15081"},{"year":"2024","school":"Ky. Wesleyan","conference":"G-MAC","division":"2","Player":"Chase Harlan","Yr":"Jr","ERA":4.5,"W":0,"L":0,"App":2,"GS":0,"SHO":0,"IP":2,"H":5,"R":3,"ER":1,"RA/9":13.5,"BB":4,"BB%":26.7,"SO":1,"SO%":6.7,"BF":15,"AB":9,"2B-A":1,"3B-A":0,"HR-A":0,"Bk":0,"WP":1,"HB":2,"IBB":0,"SO_BB_Ratio":0.25,"BAA":0.556,"OBPA":0.733,"SLGA":0.667,"SHA":0,"SFA":0,"GO":2,"FO":1,"SV":0,"teamid":574409,"conference_id":"30182","player_id":"8258979","player_url":"http://stats.ncaa.org/players/8258979?year_stat_category_id=15081"},{"year":"2024","school":"Ky. Wesleyan","conference":"G-MAC","division":"2","Player":"Tavien Tigg","Yr":"Jr","ERA":4.73,"W":1,"L":0,"App":8,"GS":0,"SHO":0,"IP":13.1,"H":14,"R":9,"ER":7,"RA/9":6.07,"BB":5,"BB%":7.8,"SO":8,"SO%":12.5,"BF":64,"AB":53,"2B-A":5,"3B-A":0,"HR-A":1,"Bk":0,"WP":1,"HB":2,"IBB":0,"SO_BB_Ratio":1.6,"BAA":0.264,"OBPA":0.339,"SLGA":0.415,"SHA":2,"SFA":2,"GO":15,"FO":16,"SV":0,"teamid":574409,"conference_id":"30182","player_id":"8285361","player_url":"http://stats.ncaa.org/players/8285361?year_stat_category_id=15081"},{"year":"2024","school":"Ky. Wesleyan","conference":"G-MAC","division":"2","Player":"Isaac Rose","Yr":"Jr","ERA":4.86,"W":3,"L":3,"App":11,"GS":7,"SHO":0,"IP":46.1,"H":42,"R":32,"ER":25,"RA/9":6.22,"BB":13,"BB%":6.4,"SO":49,"SO%":24.3,"BF":202,"AB":176,"2B-A":4,"3B-A":0,"HR-A":8,"Bk":1,"WP":1,"HB":10,"IBB":0,"SO_BB_Ratio":3.77,"BAA":0.239,"OBPA":0.325,"SLGA":0.398,"SHA":2,"SFA":1,"GO":30,"FO":53,"SV":0,"teamid":574409,"conference_id":"30182","player_id":"8285412","player_url":"http://stats.ncaa.org/players/8285412?year_stat_category_id=15081"},{"year":"2024","school":"Ky. Wesleyan","conference":"G-MAC","division":"2","Player":"Nick Judd","Yr":"So","ERA":7.15,"W":2,"L":5,"App":11,"GS":5,"SHO":0,"IP":34,"H":47,"R":33,"ER":27,"RA/9":8.74,"BB":17,"BB%":10.1,"SO":32,"SO%":19,"BF":168,"AB":145,"2B-A":6,"3B-A":4,"HR-A":2,"Bk":1,"WP":3,"HB":1,"IBB":1,"SO_BB_Ratio":1.88,"BAA":0.324,"OBPA":0.389,"SLGA":0.462,"SHA":1,"SFA":4,"GO":39,"FO":27,"SV":1,"teamid":574409,"conference_id":"30182","player_id":"8280738","player_url":"http://stats.ncaa.org/players/8280738?year_stat_category_id=15081"},{"year":"2024","school":"Ky. Wesleyan","conference":"G-MAC","division":"2","Player":"David Castleberry","Yr":"So","ERA":7,"W":1,"L":0,"App":7,"GS":0,"SHO":0,"IP":9,"H":11,"R":14,"ER":7,"RA/9":14,"BB":11,"BB%":23.4,"SO":7,"SO%":14.9,"BF":47,"AB":34,"2B-A":1,"3B-A":0,"HR-A":1,"Bk":0,"WP":0,"HB":0,"IBB":0,"SO_BB_Ratio":0.64,"BAA":0.324,"OBPA":0.478,"SLGA":0.441,"SHA":1,"SFA":1,"GO":6,"FO":11,"SV":0,"teamid":574409,"conference_id":"30182","player_id":"8283348","player_url":"http://stats.ncaa.org/players/8283348?year_stat_category_id=15081"},{"year":"2024","school":"Ky. Wesleyan","conference":"G-MAC","division":"2","Player":"Seth Wright","Yr":"Sr","ERA":3.68,"W":4,"L":3,"App":12,"GS":11,"SHO":0,"IP":71,"H":69,"R":34,"ER":29,"RA/9":4.31,"BB":30,"BB%":9.6,"SO":74,"SO%":23.8,"BF":311,"AB":270,"2B-A":15,"3B-A":0,"HR-A":5,"Bk":0,"WP":8,"HB":3,"IBB":0,"SO_BB_Ratio":2.47,"BAA":0.256,"OBPA":0.336,"SLGA":0.367,"SHA":7,"SFA":1,"GO":59,"FO":71,"SV":0,"teamid":574409,"conference_id":"30182","player_id":"8280923","player_url":"http://stats.ncaa.org/players/8280923?year_stat_category_id=15081"},{"year":"2024","school":"Ky. Wesleyan","conference":"G-MAC","division":"2","Player":"Tyler Timmermann","Yr":"Sr","ERA":4.5,"W":0,"L":0,"App":4,"GS":0,"SHO":0,"IP":2,"H":3,"R":1,"ER":1,"RA/9":4.5,"BB":0,"BB%":0,"SO":0,"SO%":0,"BF":8,"AB":6,"2B-A":0,"3B-A":0,"HR-A":0,"Bk":0,"WP":1,"HB":1,"IBB":0,"BAA":0.5,"OBPA":0.5,"SLGA":0.5,"SHA":0,"SFA":1,"GO":2,"FO":2,"SV":0,"teamid":574409,"conference_id":"30182","player_id":"8287151","player_url":"http://stats.ncaa.org/players/8287151?year_stat_category_id=15081"},{"year":"2024","school":"Ky. Wesleyan","conference":"G-MAC","division":"2","Player":"Austin Baugh","Yr":"Sr","ERA":4.5,"W":1,"L":2,"App":10,"GS":0,"SHO":0,"IP":14,"H":19,"R":11,"ER":7,"RA/9":7.07,"BB":9,"BB%":12.7,"SO":13,"SO%":18.3,"BF":71,"AB":59,"2B-A":7,"3B-A":0,"HR-A":0,"Bk":0,"WP":1,"HB":1,"IBB":0,"SO_BB_Ratio":1.44,"BAA":0.322,"OBPA":0.42,"SLGA":0.441,"SHA":2,"SFA":0,"GO":12,"FO":14,"SV":1,"teamid":574409,"conference_id":"30182","player_id":"8528256","player_url":"http://stats.ncaa.org/players/8528256?year_stat_category_id=15081"},{"year":"2024","school":"Ky. Wesleyan","conference":"G-MAC","division":"2","Player":"Josh Tucker","Yr":"Jr","ERA":7.65,"W":1,"L":5,"App":14,"GS":4,"SHO":0,"IP":37.2,"H":55,"R":41,"ER":32,"RA/9":9.8,"BB":13,"BB%":6.8,"SO":23,"SO%":12.1,"BF":190,"AB":164,"2B-A":8,"3B-A":1,"HR-A":4,"Bk":1,"WP":7,"HB":9,"IBB":2,"SO_BB_Ratio":1.77,"BAA":0.335,"OBPA":0.41,"SLGA":0.47,"SHA":2,"SFA":2,"GO":37,"FO":47,"SV":1,"teamid":574409,"conference_id":"30182","player_id":"8287421","player_url":"http://stats.ncaa.org/players/8287421?year_stat_category_id=15081"},{"year":"2024","school":"Ky. Wesleyan","conference":"G-MAC","division":"2","Player":"Connor Scheer","Yr":"Jr","ERA":7.56,"W":0,"L":0,"App":5,"GS":1,"SHO":0,"IP":8.1,"H":10,"R":10,"ER":7,"RA/9":10.8,"BB":8,"BB%":17,"SO":7,"SO%":14.9,"BF":47,"AB":36,"2B-A":3,"3B-A":0,"HR-A":2,"Bk":0,"WP":1,"HB":2,"IBB":0,"SO_BB_Ratio":0.88,"BAA":0.278,"OBPA":0.435,"SLGA":0.528,"SHA":1,"SFA":0,"GO":8,"FO":9,"SV":0,"teamid":574409,"conference_id":"30182","player_id":"8528244","player_url":"http://stats.ncaa.org/players/8528244?year_stat_category_id=15081"},{"year":"2024","school":"Ky. Wesleyan","conference":"G-MAC","division":"2","Player":"Bryant Byrd","Yr":"Jr","ERA":4.43,"W":0,"L":4,"App":13,"GS":0,"SHO":0,"IP":20.1,"H":32,"R":15,"ER":10,"RA/9":6.64,"BB":10,"BB%":9.3,"SO":20,"SO%":18.5,"BF":108,"AB":93,"2B-A":2,"3B-A":1,"HR-A":2,"Bk":0,"WP":3,"HB":3,"IBB":1,"SO_BB_Ratio":2,"BAA":0.344,"OBPA":0.425,"SLGA":0.452,"SHA":2,"SFA":0,"GO":23,"FO":17,"SV":1,"teamid":574409,"conference_id":"30182","player_id":"8528253","player_url":"http://stats.ncaa.org/players/8528253?year_stat_category_id=15081"},{"year":"2024","school":"Ky. Wesleyan","conference":"G-MAC","division":"2","Player":"Brayden Bush","Yr":"Sr","ERA":4.78,"W":2,"L":4,"App":10,"GS":8,"SHO":0,"IP":43.1,"H":45,"R":30,"ER":23,"RA/9":6.23,"BB":39,"BB%":18.3,"SO":49,"SO%":23,"BF":213,"AB":168,"2B-A":10,"3B-A":0,"HR-A":2,"Bk":1,"WP":6,"HB":2,"IBB":0,"SO_BB_Ratio":1.26,"BAA":0.268,"OBPA":0.404,"SLGA":0.363,"SHA":0,"SFA":4,"GO":40,"FO":34,"SV":0,"teamid":574409,"conference_id":"30182","player_id":"8528261","player_url":"http://stats.ncaa.org/players/8528261?year_stat_category_id=15081"}]
