[{"year":"2024","school":"Mars Hill","conference":"SAC","division":"2","Player":"Jake Wagoner Jake Wagoner","Yr":"Sr","ERA":5.37,"W":1,"L":7,"App":16,"GS":4,"SHO":0,"IP":55.1,"H":61,"R":43,"ER":33,"RA/9":6.99,"BB":21,"BB%":8.4,"SO":38,"SO%":15.1,"BF":251,"AB":215,"2B-A":6,"3B-A":1,"HR-A":6,"Bk":1,"WP":4,"HB":11,"IBB":0,"SO_BB_Ratio":1.81,"BAA":0.284,"OBPA":0.373,"SLGA":0.405,"SHA":2,"SFA":2,"GO":68,"FO":46,"SV":1,"teamid":574248,"conference_id":"12850","player_id":"8261947","player_url":"http://stats.ncaa.org/players/8261947?year_stat_category_id=15081"},{"year":"2024","school":"Mars Hill","conference":"SAC","division":"2","Player":"Brian Smart Brian Smart","Yr":"Sr","ERA":3.96,"W":1,"L":1,"App":20,"GS":6,"SHO":0,"IP":36.1,"H":32,"R":16,"ER":16,"RA/9":3.96,"BB":21,"BB%":12.9,"SO":25,"SO%":15.3,"BF":163,"AB":133,"2B-A":4,"3B-A":4,"HR-A":3,"Bk":0,"WP":5,"HB":6,"IBB":0,"SO_BB_Ratio":1.19,"BAA":0.241,"OBPA":0.366,"SLGA":0.398,"SHA":2,"SFA":1,"GO":31,"FO":48,"SV":0,"teamid":574248,"conference_id":"12850","player_id":"8271290","player_url":"http://stats.ncaa.org/players/8271290?year_stat_category_id=15081"},{"year":"2024","school":"Mars Hill","conference":"SAC","division":"2","Player":"Donald Gorgei Donald Gorgei","Yr":"So","ERA":6.23,"W":1,"L":0,"App":9,"GS":2,"SHO":0,"IP":13,"H":11,"R":9,"ER":9,"RA/9":6.23,"BB":9,"BB%":15.3,"SO":10,"SO%":16.9,"BF":59,"AB":46,"2B-A":4,"3B-A":2,"HR-A":1,"Bk":0,"WP":4,"HB":3,"IBB":0,"SO_BB_Ratio":1.11,"BAA":0.239,"OBPA":0.39,"SLGA":0.478,"SHA":0,"SFA":1,"GO":14,"FO":12,"SV":0,"teamid":574248,"conference_id":"12850","player_id":"8264513","player_url":"http://stats.ncaa.org/players/8264513?year_stat_category_id=15081"},{"year":"2024","school":"Mars Hill","conference":"SAC","division":"2","Player":"Gavin Raab Gavin Raab","Yr":"So","ERA":33.75,"W":0,"L":0,"App":2,"GS":0,"SHO":0,"IP":1.1,"H":4,"R":5,"ER":5,"RA/9":33.75,"BB":3,"BB%":25,"SO":3,"SO%":25,"BF":12,"AB":8,"2B-A":1,"3B-A":0,"HR-A":2,"Bk":0,"WP":0,"HB":1,"IBB":0,"SO_BB_Ratio":1,"BAA":0.5,"OBPA":0.667,"SLGA":1.375,"SHA":0,"SFA":0,"GO":0,"FO":1,"SV":0,"teamid":574248,"conference_id":"12850","player_id":"8276514","player_url":"http://stats.ncaa.org/players/8276514?year_stat_category_id=15081"},{"year":"2024","school":"Mars Hill","conference":"SAC","division":"2","Player":"Colin McCaw Colin McCaw","Yr":"So","ERA":6.75,"W":1,"L":0,"App":13,"GS":1,"SHO":0,"IP":20,"H":21,"R":15,"ER":15,"RA/9":6.75,"BB":18,"BB%":18,"SO":14,"SO%":14,"BF":100,"AB":74,"2B-A":5,"3B-A":0,"HR-A":2,"Bk":0,"WP":8,"HB":6,"IBB":0,"SO_BB_Ratio":0.78,"BAA":0.284,"OBPA":0.45,"SLGA":0.432,"SHA":0,"SFA":2,"GO":23,"FO":18,"SV":0,"teamid":574248,"conference_id":"12850","player_id":"8263911","player_url":"http://stats.ncaa.org/players/8263911?year_stat_category_id=15081"},{"year":"2024","school":"Mars Hill","conference":"SAC","division":"2","Player":"Ahmad Tucker Ahmad Tucker","Yr":"Sr","ERA":20.25,"W":0,"L":0,"App":4,"GS":0,"SHO":0,"IP":5.1,"H":6,"R":13,"ER":12,"RA/9":21.94,"BB":5,"BB%":15.6,"SO":3,"SO%":9.4,"BF":32,"AB":20,"2B-A":4,"3B-A":0,"HR-A":1,"Bk":0,"WP":1,"HB":4,"IBB":0,"SO_BB_Ratio":0.6,"BAA":0.3,"OBPA":0.469,"SLGA":0.65,"SHA":0,"SFA":3,"GO":7,"FO":6,"SV":0,"teamid":574248,"conference_id":"12850","player_id":"8267678","player_url":"http://stats.ncaa.org/players/8267678?year_stat_category_id=15081"},{"year":"2024","school":"Mars Hill","conference":"SAC","division":"2","Player":"Nate Crissey Nate Crissey","Yr":"Sr","ERA":5.55,"W":4,"L":2,"App":14,"GS":2,"SHO":0,"IP":24.1,"H":20,"R":18,"ER":15,"RA/9":6.66,"BB":20,"BB%":16.8,"SO":22,"SO%":18.5,"BF":119,"AB":93,"2B-A":4,"3B-A":0,"HR-A":3,"Bk":0,"WP":7,"HB":3,"IBB":0,"SO_BB_Ratio":1.1,"BAA":0.215,"OBPA":0.361,"SLGA":0.355,"SHA":0,"SFA":3,"GO":19,"FO":32,"SV":0,"teamid":574248,"conference_id":"12850","player_id":"8272158","player_url":"http://stats.ncaa.org/players/8272158?year_stat_category_id=15081"},{"year":"2024","school":"Mars Hill","conference":"SAC","division":"2","Player":"Dustin Dunlap Dustin Dunlap","Yr":"So","ERA":7.27,"W":1,"L":0,"App":8,"GS":1,"SHO":0,"IP":8.2,"H":9,"R":10,"ER":7,"RA/9":10.38,"BB":6,"BB%":15,"SO":6,"SO%":15,"BF":40,"AB":32,"2B-A":1,"3B-A":0,"HR-A":3,"Bk":0,"WP":1,"HB":1,"IBB":0,"SO_BB_Ratio":1,"BAA":0.281,"OBPA":0.41,"SLGA":0.594,"SHA":1,"SFA":0,"GO":8,"FO":9,"SV":0,"teamid":574248,"conference_id":"12850","player_id":"8269748","player_url":"http://stats.ncaa.org/players/8269748?year_stat_category_id=15081"},{"year":"2024","school":"Mars Hill","conference":"SAC","division":"2","Player":"Dearl Edens Dearl Edens","Yr":"So","ERA":7.24,"W":1,"L":2,"App":6,"GS":3,"SHO":0,"IP":13.2,"H":23,"R":18,"ER":11,"RA/9":11.85,"BB":11,"BB%":14.1,"SO":16,"SO%":20.5,"BF":78,"AB":63,"2B-A":8,"3B-A":0,"HR-A":1,"Bk":0,"WP":0,"HB":2,"IBB":1,"SO_BB_Ratio":1.45,"BAA":0.365,"OBPA":0.468,"SLGA":0.54,"SHA":1,"SFA":1,"GO":8,"FO":15,"SV":1,"teamid":574248,"conference_id":"12850","player_id":"8265537","player_url":"http://stats.ncaa.org/players/8265537?year_stat_category_id=15081"},{"year":"2024","school":"Mars Hill","conference":"SAC","division":"2","Player":"Barrett Williams Barrett Williams","Yr":"Sr","ERA":8.44,"W":0,"L":1,"App":2,"GS":1,"SHO":0,"IP":5.1,"H":6,"R":6,"ER":5,"RA/9":10.13,"BB":6,"BB%":23.1,"SO":6,"SO%":23.1,"BF":26,"AB":20,"2B-A":1,"3B-A":0,"HR-A":0,"Bk":0,"WP":1,"HB":0,"IBB":0,"SO_BB_Ratio":1,"BAA":0.3,"OBPA":0.462,"SLGA":0.35,"SHA":0,"SFA":0,"GO":3,"FO":6,"SV":0,"teamid":574248,"conference_id":"12850","player_id":"8287444","player_url":"http://stats.ncaa.org/players/8287444?year_stat_category_id=15081"},{"year":"2024","school":"Mars Hill","conference":"SAC","division":"2","Player":"Owen Bynum Owen Bynum","Yr":"So","ERA":4.76,"W":0,"L":0,"App":13,"GS":0,"SHO":0,"IP":17,"H":18,"R":10,"ER":9,"RA/9":5.29,"BB":7,"BB%":8.5,"SO":8,"SO%":9.8,"BF":82,"AB":65,"2B-A":2,"3B-A":0,"HR-A":2,"Bk":0,"WP":0,"HB":7,"IBB":0,"SO_BB_Ratio":1.14,"BAA":0.277,"OBPA":0.39,"SLGA":0.4,"SHA":0,"SFA":3,"GO":12,"FO":27,"SV":1,"teamid":574248,"conference_id":"12850","player_id":"8279013","player_url":"http://stats.ncaa.org/players/8279013?year_stat_category_id=15081"},{"year":"2024","school":"Mars Hill","conference":"SAC","division":"2","Player":"Nolan Jamison Nolan Jamison","Yr":"Jr","ERA":40.5,"W":0,"L":0,"App":2,"GS":0,"SHO":0,"IP":0.2,"H":1,"R":4,"ER":3,"RA/9":54,"BB":2,"BB%":28.6,"SO":0,"SO%":0,"BF":7,"AB":4,"2B-A":1,"3B-A":0,"HR-A":0,"Bk":1,"WP":1,"HB":1,"IBB":0,"SO_BB_Ratio":0,"BAA":0.25,"OBPA":0.571,"SLGA":0.5,"SHA":0,"SFA":0,"GO":1,"FO":1,"SV":0,"teamid":574248,"conference_id":"12850","player_id":"8287730","player_url":"http://stats.ncaa.org/players/8287730?year_stat_category_id=15081"},{"year":"2024","school":"Mars Hill","conference":"SAC","division":"2","Player":"Grady Bivens Grady Bivens","Yr":"So","ERA":11.29,"W":4,"L":5,"App":14,"GS":9,"SHO":0,"IP":36.2,"H":41,"R":53,"ER":46,"RA/9":13.01,"BB":36,"BB%":18,"SO":28,"SO%":14,"BF":200,"AB":149,"2B-A":7,"3B-A":0,"HR-A":8,"Bk":0,"WP":7,"HB":13,"IBB":0,"SO_BB_Ratio":0.78,"BAA":0.275,"OBPA":0.452,"SLGA":0.483,"SHA":1,"SFA":1,"GO":41,"FO":38,"SV":0,"teamid":574248,"conference_id":"12850","player_id":"8280148","player_url":"http://stats.ncaa.org/players/8280148?year_stat_category_id=15081"},{"year":"2024","school":"Mars Hill","conference":"SAC","division":"2","Player":"Brennan Williams Brennan Williams","Yr":"Fr","ERA":6.14,"W":2,"L":6,"App":12,"GS":12,"SHO":1,"IP":55.2,"H":65,"R":51,"ER":38,"RA/9":8.25,"BB":29,"BB%":11.1,"SO":39,"SO%":14.9,"BF":262,"AB":225,"2B-A":12,"3B-A":2,"HR-A":5,"Bk":1,"WP":7,"HB":2,"IBB":1,"SO_BB_Ratio":1.34,"BAA":0.289,"OBPA":0.372,"SLGA":0.427,"SHA":4,"SFA":2,"GO":53,"FO":63,"SV":0,"teamid":574248,"conference_id":"12850","player_id":"8407141","player_url":"http://stats.ncaa.org/players/8407141?year_stat_category_id=15081"},{"year":"2024","school":"Mars Hill","conference":"SAC","division":"2","Player":"Brady Stephens Brady Stephens","Yr":"Fr","ERA":5.48,"W":0,"L":1,"App":25,"GS":0,"SHO":0,"IP":21.1,"H":24,"R":15,"ER":13,"RA/9":6.33,"BB":8,"BB%":8.2,"SO":9,"SO%":9.2,"BF":98,"AB":81,"2B-A":4,"3B-A":1,"HR-A":3,"Bk":0,"WP":2,"HB":7,"IBB":4,"SO_BB_Ratio":1.12,"BAA":0.296,"OBPA":0.402,"SLGA":0.481,"SHA":1,"SFA":1,"GO":23,"FO":26,"SV":0,"teamid":574248,"conference_id":"12850","player_id":"8407145","player_url":"http://stats.ncaa.org/players/8407145?year_stat_category_id=15081"},{"year":"2024","school":"Mars Hill","conference":"SAC","division":"2","Player":"Jordan Searcy Jordan Searcy","Yr":"Jr","ERA":6.75,"W":0,"L":1,"App":5,"GS":1,"SHO":0,"IP":5.1,"H":10,"R":4,"ER":4,"RA/9":6.75,"BB":2,"BB%":7.1,"SO":4,"SO%":14.3,"BF":28,"AB":24,"2B-A":4,"3B-A":0,"HR-A":1,"Bk":0,"WP":0,"HB":2,"IBB":0,"SO_BB_Ratio":2,"BAA":0.417,"OBPA":0.5,"SLGA":0.708,"SHA":0,"SFA":0,"GO":3,"FO":7,"SV":0,"teamid":574248,"conference_id":"12850","player_id":"8407132","player_url":"http://stats.ncaa.org/players/8407132?year_stat_category_id=15081"},{"year":"2024","school":"Mars Hill","conference":"SAC","division":"2","Player":"Landen Moore Landen Moore","Yr":"Fr","ERA":10.13,"W":0,"L":3,"App":9,"GS":5,"SHO":0,"IP":18.2,"H":30,"R":21,"ER":21,"RA/9":10.13,"BB":9,"BB%":9.3,"SO":9,"SO%":9.3,"BF":97,"AB":78,"2B-A":4,"3B-A":0,"HR-A":2,"Bk":0,"WP":1,"HB":8,"IBB":0,"SO_BB_Ratio":1,"BAA":0.385,"OBPA":0.49,"SLGA":0.513,"SHA":1,"SFA":1,"GO":21,"FO":20,"SV":1,"teamid":574248,"conference_id":"12850","player_id":"8407137","player_url":"http://stats.ncaa.org/players/8407137?year_stat_category_id=15081"},{"year":"2024","school":"Mars Hill","conference":"SAC","division":"2","Player":"Brycen Jewell Brycen Jewell","Yr":"Sr","ERA":20.52,"W":0,"L":1,"App":7,"GS":1,"SHO":0,"IP":8.1,"H":13,"R":20,"ER":19,"RA/9":21.6,"BB":14,"BB%":25.9,"SO":8,"SO%":14.8,"BF":54,"AB":38,"2B-A":4,"3B-A":1,"HR-A":3,"Bk":0,"WP":3,"HB":1,"IBB":0,"SO_BB_Ratio":0.57,"BAA":0.342,"OBPA":0.519,"SLGA":0.737,"SHA":0,"SFA":1,"GO":10,"FO":8,"SV":1,"teamid":574248,"conference_id":"12850","player_id":"8407126","player_url":"http://stats.ncaa.org/players/8407126?year_stat_category_id=15081"},{"year":"2024","school":"Mars Hill","conference":"SAC","division":"2","Player":"Peyton Kowalski Peyton Kowalski","Yr":"Fr","ERA":4.96,"W":2,"L":1,"App":10,"GS":2,"SHO":0,"IP":16.1,"H":16,"R":11,"ER":9,"RA/9":6.06,"BB":15,"BB%":19.2,"SO":13,"SO%":16.7,"BF":78,"AB":58,"2B-A":2,"3B-A":0,"HR-A":3,"Bk":0,"WP":5,"HB":0,"IBB":0,"SO_BB_Ratio":0.87,"BAA":0.276,"OBPA":0.408,"SLGA":0.466,"SHA":2,"SFA":3,"GO":13,"FO":20,"SV":0,"teamid":574248,"conference_id":"12850","player_id":"8407147","player_url":"http://stats.ncaa.org/players/8407147?year_stat_category_id=15081"},{"year":"2024","school":"Mars Hill","conference":"SAC","division":"2","Player":"Philip Devita Philip Devita","Yr":"Fr","ERA":3.09,"W":0,"L":0,"App":8,"GS":0,"SHO":0,"IP":11.2,"H":6,"R":6,"ER":4,"RA/9":4.63,"BB":10,"BB%":18.9,"SO":7,"SO%":13.2,"BF":53,"AB":40,"2B-A":1,"3B-A":0,"HR-A":2,"Bk":0,"WP":2,"HB":2,"IBB":0,"SO_BB_Ratio":0.7,"BAA":0.15,"OBPA":0.34,"SLGA":0.325,"SHA":0,"SFA":1,"GO":12,"FO":14,"SV":0,"teamid":574248,"conference_id":"12850","player_id":"8407150","player_url":"http://stats.ncaa.org/players/8407150?year_stat_category_id=15081"},{"year":"2024","school":"Mars Hill","conference":"SAC","division":"2","Player":"Quinn Rembert Quinn Rembert","Yr":"So","ERA":18,"W":0,"L":0,"App":1,"GS":0,"SHO":0,"IP":2,"H":5,"R":5,"ER":4,"RA/9":22.5,"BB":2,"BB%":13.3,"SO":3,"SO%":20,"BF":15,"AB":11,"2B-A":2,"3B-A":0,"HR-A":0,"Bk":0,"WP":2,"HB":1,"IBB":0,"SO_BB_Ratio":1.5,"BAA":0.455,"OBPA":0.533,"SLGA":0.636,"SHA":0,"SFA":1,"GO":1,"FO":2,"SV":0,"teamid":574248,"conference_id":"12850","player_id":"8407133","player_url":"http://stats.ncaa.org/players/8407133?year_stat_category_id=15081"},{"year":"2024","school":"Mars Hill","conference":"SAC","division":"2","Player":"David Ziolkowski David Ziolkowski","Yr":"Fr","ERA":14.29,"W":0,"L":0,"App":6,"GS":0,"SHO":0,"IP":5.2,"H":5,"R":9,"ER":9,"RA/9":14.29,"BB":8,"BB%":24.2,"SO":4,"SO%":12.1,"BF":33,"AB":21,"2B-A":2,"3B-A":0,"HR-A":2,"Bk":0,"WP":2,"HB":3,"IBB":0,"SO_BB_Ratio":0.5,"BAA":0.238,"OBPA":0.5,"SLGA":0.619,"SHA":1,"SFA":0,"GO":8,"FO":5,"SV":0,"teamid":574248,"conference_id":"12850","player_id":"8407152","player_url":"http://stats.ncaa.org/players/8407152?year_stat_category_id=15081"},{"year":"2024","school":"Mars Hill","conference":"SAC","division":"2","Player":"JD Lewis JD Lewis","Yr":"So","ERA":11.2,"W":0,"L":1,"App":13,"GS":0,"SHO":0,"IP":13.2,"H":20,"R":18,"ER":17,"RA/9":11.85,"BB":13,"BB%":18.1,"SO":6,"SO%":8.3,"BF":72,"AB":56,"2B-A":5,"3B-A":1,"HR-A":3,"Bk":0,"WP":1,"HB":3,"IBB":1,"SO_BB_Ratio":0.46,"BAA":0.357,"OBPA":0.5,"SLGA":0.643,"SHA":0,"SFA":0,"GO":14,"FO":14,"SV":1,"teamid":574248,"conference_id":"12850","player_id":"8407134","player_url":"http://stats.ncaa.org/players/8407134?year_stat_category_id=15081"}]
