[{"year":"2024","school":"Union (TN)","conference":"Gulf South","division":"2","Player":"Jake Jewell Jake Jewell","Yr":"Jr","ERA":21.6,"W":0,"L":1,"App":3,"GS":0,"SHO":0,"IP":1.2,"H":2,"R":4,"ER":4,"RA/9":21.6,"BB":2,"BB%":20,"SO":1,"SO%":10,"BF":10,"AB":7,"2B-A":0,"3B-A":1,"HR-A":0,"Bk":0,"WP":2,"HB":0,"IBB":0,"SO_BB_Ratio":0.5,"BAA":0.286,"OBPA":0.444,"SLGA":0.571,"SHA":1,"SFA":0,"GO":2,"FO":2,"SV":0,"teamid":574343,"conference_id":"858","player_id":"8266866","player_url":"http://stats.ncaa.org/players/8266866?year_stat_category_id=15081"},{"year":"2024","school":"Union (TN)","conference":"Gulf South","division":"2","Player":"Billy Beckham Billy Beckham","Yr":"Jr","ERA":18,"W":0,"L":0,"App":2,"GS":0,"SHO":0,"IP":1,"H":3,"R":2,"ER":2,"RA/9":18,"BB":0,"BB%":0,"SO":0,"SO%":0,"BF":7,"AB":6,"2B-A":0,"3B-A":0,"HR-A":2,"Bk":0,"WP":0,"HB":1,"IBB":0,"BAA":0.5,"OBPA":0.571,"SLGA":1.5,"SHA":0,"SFA":0,"GO":1,"FO":2,"SV":0,"teamid":574343,"conference_id":"858","player_id":"8277968","player_url":"http://stats.ncaa.org/players/8277968?year_stat_category_id=15081"},{"year":"2024","school":"Union (TN)","conference":"Gulf South","division":"2","Player":"Lane Evans Lane Evans","Yr":"So","ERA":10.23,"W":1,"L":3,"App":15,"GS":5,"SHO":0,"IP":31.2,"H":42,"R":36,"ER":36,"RA/9":10.23,"BB":28,"BB%":17.2,"SO":22,"SO%":13.5,"BF":163,"AB":126,"2B-A":4,"3B-A":1,"HR-A":4,"Bk":0,"WP":8,"HB":4,"IBB":0,"SO_BB_Ratio":0.79,"BAA":0.333,"OBPA":0.462,"SLGA":0.476,"SHA":3,"SFA":2,"GO":40,"FO":26,"SV":1,"teamid":574343,"conference_id":"858","player_id":"8261262","player_url":"http://stats.ncaa.org/players/8261262?year_stat_category_id=15081"},{"year":"2024","school":"Union (TN)","conference":"Gulf South","division":"2","Player":"S. Galbraith S. Galbraith","Yr":"So","ERA":9,"W":1,"L":0,"App":5,"GS":0,"SHO":0,"IP":3,"H":1,"R":5,"ER":3,"RA/9":15,"BB":0,"BB%":0,"SO":2,"SO%":13.3,"BF":15,"AB":10,"2B-A":0,"3B-A":0,"HR-A":1,"Bk":0,"WP":0,"HB":4,"IBB":0,"BAA":0.1,"OBPA":0.333,"SLGA":0.4,"SHA":0,"SFA":1,"GO":5,"FO":2,"SV":0,"teamid":574343,"conference_id":"858","player_id":"8262445","player_url":"http://stats.ncaa.org/players/8262445?year_stat_category_id=15081"},{"year":"2024","school":"Union (TN)","conference":"Gulf South","division":"2","Player":"Ethan Orwig Ethan Orwig","Yr":"Jr","ERA":7.71,"W":2,"L":2,"App":19,"GS":0,"SHO":0,"IP":18.2,"H":23,"R":18,"ER":16,"RA/9":8.68,"BB":13,"BB%":13.1,"SO":19,"SO%":19.2,"BF":99,"AB":77,"2B-A":4,"3B-A":1,"HR-A":1,"Bk":1,"WP":7,"HB":9,"IBB":1,"SO_BB_Ratio":1.46,"BAA":0.299,"OBPA":0.455,"SLGA":0.416,"SHA":0,"SFA":0,"GO":17,"FO":15,"SV":0,"teamid":574343,"conference_id":"858","player_id":"8275484","player_url":"http://stats.ncaa.org/players/8275484?year_stat_category_id=15081"},{"year":"2024","school":"Union (TN)","conference":"Gulf South","division":"2","Player":"Sam Poindexter Sam Poindexter","Yr":"Sr","ERA":6.82,"W":3,"L":0,"App":12,"GS":12,"SHO":0,"IP":64.2,"H":92,"R":53,"ER":49,"RA/9":7.38,"BB":36,"BB%":11.4,"SO":44,"SO%":13.9,"BF":317,"AB":268,"2B-A":18,"3B-A":3,"HR-A":5,"Bk":2,"WP":6,"HB":6,"IBB":1,"SO_BB_Ratio":1.22,"BAA":0.343,"OBPA":0.427,"SLGA":0.489,"SHA":3,"SFA":4,"GO":60,"FO":78,"SV":0,"teamid":574343,"conference_id":"858","player_id":"8277134","player_url":"http://stats.ncaa.org/players/8277134?year_stat_category_id=15081"},{"year":"2024","school":"Union (TN)","conference":"Gulf South","division":"2","Player":"Ryan Evans Ryan Evans","Yr":"Jr","ERA":6.55,"W":3,"L":2,"App":20,"GS":0,"SHO":0,"IP":34.1,"H":43,"R":31,"ER":25,"RA/9":8.13,"BB":16,"BB%":9.4,"SO":21,"SO%":12.4,"BF":170,"AB":134,"2B-A":6,"3B-A":2,"HR-A":4,"Bk":0,"WP":6,"HB":14,"IBB":1,"SO_BB_Ratio":1.31,"BAA":0.321,"OBPA":0.435,"SLGA":0.485,"SHA":2,"SFA":4,"GO":43,"FO":31,"SV":2,"teamid":574343,"conference_id":"858","player_id":"8268296","player_url":"http://stats.ncaa.org/players/8268296?year_stat_category_id=15081"},{"year":"2024","school":"Union (TN)","conference":"Gulf South","division":"2","Player":"Eli Snelson Eli Snelson","Yr":"Sr","ERA":6.78,"W":4,"L":5,"App":13,"GS":12,"SHO":0,"IP":69,"H":83,"R":60,"ER":52,"RA/9":7.83,"BB":40,"BB%":12.2,"SO":57,"SO%":17.4,"BF":328,"AB":275,"2B-A":27,"3B-A":7,"HR-A":8,"Bk":0,"WP":5,"HB":4,"IBB":3,"SO_BB_Ratio":1.43,"BAA":0.302,"OBPA":0.394,"SLGA":0.538,"SHA":6,"SFA":3,"GO":78,"FO":57,"SV":0,"teamid":574343,"conference_id":"858","player_id":"8287021","player_url":"http://stats.ncaa.org/players/8287021?year_stat_category_id=15081"},{"year":"2024","school":"Union (TN)","conference":"Gulf South","division":"2","Player":"Jamal Allen Jamal Allen","Yr":"Sr","ERA":6.33,"W":1,"L":4,"App":19,"GS":0,"SHO":0,"IP":21.1,"H":24,"R":15,"ER":15,"RA/9":6.33,"BB":19,"BB%":17.4,"SO":15,"SO%":13.8,"BF":109,"AB":84,"2B-A":6,"3B-A":0,"HR-A":4,"Bk":0,"WP":12,"HB":6,"IBB":2,"SO_BB_Ratio":0.79,"BAA":0.286,"OBPA":0.45,"SLGA":0.5,"SHA":0,"SFA":0,"GO":19,"FO":25,"SV":5,"teamid":574343,"conference_id":"858","player_id":"8424099","player_url":"http://stats.ncaa.org/players/8424099?year_stat_category_id=15081"},{"year":"2024","school":"Union (TN)","conference":"Gulf South","division":"2","Player":"Noah Toney Noah Toney","Yr":"So","ERA":8.41,"W":1,"L":7,"App":13,"GS":12,"SHO":1,"IP":55.2,"H":78,"R":59,"ER":52,"RA/9":9.54,"BB":29,"BB%":10.4,"SO":30,"SO%":10.8,"BF":278,"AB":234,"2B-A":16,"3B-A":2,"HR-A":8,"Bk":0,"WP":3,"HB":10,"IBB":1,"SO_BB_Ratio":1.03,"BAA":0.333,"OBPA":0.425,"SLGA":0.521,"SHA":3,"SFA":2,"GO":55,"FO":75,"SV":0,"teamid":574343,"conference_id":"858","player_id":"8424110","player_url":"http://stats.ncaa.org/players/8424110?year_stat_category_id=15081"},{"year":"2024","school":"Union (TN)","conference":"Gulf South","division":"2","Player":"Brody Mann Brody Mann","Yr":"Fr","ERA":13.19,"W":1,"L":2,"App":11,"GS":2,"SHO":0,"IP":14.1,"H":20,"R":21,"ER":21,"RA/9":13.19,"BB":15,"BB%":18.1,"SO":9,"SO%":10.8,"BF":83,"AB":57,"2B-A":4,"3B-A":0,"HR-A":1,"Bk":0,"WP":11,"HB":10,"IBB":0,"SO_BB_Ratio":0.6,"BAA":0.351,"OBPA":0.542,"SLGA":0.474,"SHA":0,"SFA":1,"GO":14,"FO":14,"SV":0,"teamid":574343,"conference_id":"858","player_id":"8424119","player_url":"http://stats.ncaa.org/players/8424119?year_stat_category_id=15081"},{"year":"2024","school":"Union (TN)","conference":"Gulf South","division":"2","Player":"Cole Smith Cole Smith","Yr":"Fr","ERA":3.63,"W":0,"L":0,"App":12,"GS":1,"SHO":0,"IP":17.1,"H":9,"R":7,"ER":7,"RA/9":3.63,"BB":19,"BB%":24.1,"SO":9,"SO%":11.4,"BF":79,"AB":55,"2B-A":1,"3B-A":1,"HR-A":1,"Bk":0,"WP":4,"HB":4,"IBB":0,"SO_BB_Ratio":0.47,"BAA":0.164,"OBPA":0.405,"SLGA":0.273,"SHA":0,"SFA":1,"GO":19,"FO":19,"SV":0,"teamid":574343,"conference_id":"858","player_id":"8424122","player_url":"http://stats.ncaa.org/players/8424122?year_stat_category_id=15081"},{"year":"2024","school":"Union (TN)","conference":"Gulf South","division":"2","Player":"Cody Tjomsland Cody Tjomsland","Yr":"Fr","ERA":9.82,"W":0,"L":1,"App":4,"GS":0,"SHO":0,"IP":3.2,"H":8,"R":8,"ER":4,"RA/9":19.64,"BB":6,"BB%":24,"SO":0,"SO%":0,"BF":25,"AB":16,"2B-A":0,"3B-A":0,"HR-A":0,"Bk":0,"WP":1,"HB":1,"IBB":1,"SO_BB_Ratio":0,"BAA":0.5,"OBPA":0.625,"SLGA":0.5,"SHA":1,"SFA":1,"GO":4,"FO":5,"SV":0,"teamid":574343,"conference_id":"858","player_id":"8424127","player_url":"http://stats.ncaa.org/players/8424127?year_stat_category_id=15081"},{"year":"2024","school":"Union (TN)","conference":"Gulf South","division":"2","Player":"Chase Spears Chase Spears","Yr":"Fr","ERA":38.57,"W":0,"L":0,"App":5,"GS":0,"SHO":0,"IP":2.1,"H":3,"R":10,"ER":10,"RA/9":38.57,"BB":7,"BB%":35,"SO":0,"SO%":0,"BF":20,"AB":10,"2B-A":1,"3B-A":0,"HR-A":0,"Bk":0,"WP":2,"HB":3,"IBB":0,"SO_BB_Ratio":0,"BAA":0.3,"OBPA":0.65,"SLGA":0.4,"SHA":0,"SFA":0,"GO":2,"FO":5,"SV":0,"teamid":574343,"conference_id":"858","player_id":"8424150","player_url":"http://stats.ncaa.org/players/8424150?year_stat_category_id=15081"},{"year":"2024","school":"Union (TN)","conference":"Gulf South","division":"2","Player":"Alex  Johnson Alex  Johnson","Yr":"Fr","ERA":3.86,"W":0,"L":0,"App":7,"GS":0,"SHO":0,"IP":7,"H":5,"R":4,"ER":3,"RA/9":5.14,"BB":6,"BB%":19.4,"SO":5,"SO%":16.1,"BF":31,"AB":23,"2B-A":1,"3B-A":0,"HR-A":1,"Bk":0,"WP":0,"HB":1,"IBB":0,"SO_BB_Ratio":0.83,"BAA":0.217,"OBPA":0.4,"SLGA":0.391,"SHA":1,"SFA":0,"GO":4,"FO":9,"SV":0,"teamid":574343,"conference_id":"858","player_id":"8424157","player_url":"http://stats.ncaa.org/players/8424157?year_stat_category_id=15081"},{"year":"2024","school":"Union (TN)","conference":"Gulf South","division":"2","Player":"Scotty Wyatt Scotty Wyatt","Yr":"Fr","ERA":8.22,"W":0,"L":2,"App":13,"GS":2,"SHO":0,"IP":23,"H":33,"R":26,"ER":21,"RA/9":10.17,"BB":26,"BB%":19.3,"SO":17,"SO%":12.6,"BF":135,"AB":101,"2B-A":6,"3B-A":3,"HR-A":0,"Bk":0,"WP":11,"HB":5,"IBB":0,"SO_BB_Ratio":0.65,"BAA":0.327,"OBPA":0.481,"SLGA":0.446,"SHA":2,"SFA":1,"GO":22,"FO":27,"SV":0,"teamid":574343,"conference_id":"858","player_id":"8424140","player_url":"http://stats.ncaa.org/players/8424140?year_stat_category_id=15081"},{"year":"2024","school":"Union (TN)","conference":"Gulf South","division":"2","Player":"Jack Rasmussen Jack Rasmussen","Yr":"Sr","ERA":27,"W":0,"L":0,"App":7,"GS":0,"SHO":0,"IP":3.2,"H":4,"R":15,"ER":11,"RA/9":36.82,"BB":8,"BB%":25.8,"SO":0,"SO%":0,"BF":31,"AB":13,"2B-A":1,"3B-A":0,"HR-A":1,"Bk":0,"WP":5,"HB":8,"IBB":0,"SO_BB_Ratio":0,"BAA":0.308,"OBPA":0.667,"SLGA":0.615,"SHA":1,"SFA":1,"GO":7,"FO":3,"SV":0,"teamid":574343,"conference_id":"858","player_id":"8424221","player_url":"http://stats.ncaa.org/players/8424221?year_stat_category_id=15081"}]
