[{"year":"2024","school":"Notre Dame (OH)","conference":"MEC","division":"2","Jersey":"19","Player":"Sean Fernald","Yr":"Jr","Pos":"UT","GP":4,"GS":2,"PA":8,"BA":0,"OBP":0.125,"SLG":0,"OPS":0.125,"AB":7,"R":0,"H":0,"1B":0,"2B":0,"3B":0,"TB":0,"HR":0,"RBI":0,"BB":1,"BB%":12.5,"HBP":0,"SF":0,"SH":0,"K":4,"K%":50,"DP":0,"CS":0,"SB":0,"BABIP":0,"ISO":0,"teamid":574333,"conference_id":"30183","player_id":"8266767","player_url":"http://stats.ncaa.org/players/8266767?year_stat_category_id=15080"},{"year":"2024","school":"Notre Dame (OH)","conference":"MEC","division":"2","Jersey":"96","Player":"Jackson Smetak","Yr":"Fr","Pos":"1B","GP":13,"GS":12,"PA":37,"BA":0.313,"OBP":0.405,"SLG":0.438,"OPS":0.843,"AB":32,"R":3,"H":10,"1B":6,"2B":4,"3B":0,"TB":14,"HR":0,"RBI":4,"BB":5,"BB%":13.5,"HBP":0,"SF":0,"SH":0,"K":9,"K%":24.3,"DP":1,"CS":0,"SB":1,"BABIP":0.435,"ISO":0.125,"teamid":574333,"conference_id":"30183","player_id":"8528677","player_url":"http://stats.ncaa.org/players/8528677?year_stat_category_id=15080"},{"year":"2024","school":"Notre Dame (OH)","conference":"MEC","division":"2","Jersey":"16","Player":"Johnathan Cook","Yr":"Jr","Pos":"UT","GP":20,"GS":5,"PA":16,"BA":0.308,"OBP":0.438,"SLG":0.385,"OPS":0.823,"AB":13,"R":1,"H":4,"1B":3,"2B":1,"3B":0,"TB":5,"HR":0,"RBI":1,"BB":3,"BB%":18.8,"HBP":0,"SF":0,"SH":0,"K":1,"K%":6.2,"DP":0,"CS":0,"SB":0,"BABIP":0.333,"ISO":0.077,"teamid":574333,"conference_id":"30183","player_id":"8271594","player_url":"http://stats.ncaa.org/players/8271594?year_stat_category_id=15080"},{"year":"2024","school":"Notre Dame (OH)","conference":"MEC","division":"2","Jersey":"1","Player":"Carson Petrecca","Yr":"Fr","Pos":"INF","GP":50,"GS":50,"PA":188,"BA":0.255,"OBP":0.38,"SLG":0.379,"OPS":0.759,"AB":153,"R":22,"H":39,"1B":29,"2B":5,"3B":1,"TB":58,"HR":4,"RBI":34,"BB":28,"BB%":14.9,"HBP":4,"SF":2,"SH":1,"K":30,"K%":16,"DP":6,"CS":1,"SB":4,"BABIP":0.289,"ISO":0.124,"teamid":574333,"conference_id":"30183","player_id":"8528640","player_url":"http://stats.ncaa.org/players/8528640?year_stat_category_id=15080"},{"year":"2024","school":"Notre Dame (OH)","conference":"MEC","division":"2","Jersey":"17","Player":"Devon Morris","Yr":"Fr","Pos":"C","GP":40,"GS":32,"PA":125,"BA":0.269,"OBP":0.384,"SLG":0.356,"OPS":0.74,"AB":104,"R":21,"H":28,"1B":22,"2B":4,"3B":1,"TB":37,"HR":1,"RBI":13,"BB":18,"BB%":14.4,"HBP":2,"SF":1,"SH":0,"K":22,"K%":17.6,"DP":4,"CS":0,"SB":4,"BABIP":0.329,"ISO":0.087,"teamid":574333,"conference_id":"30183","player_id":"8528657","player_url":"http://stats.ncaa.org/players/8528657?year_stat_category_id=15080"},{"year":"2024","school":"Notre Dame (OH)","conference":"MEC","division":"2","Jersey":"18","Player":"Michael Vertino","Yr":"Fr","Pos":"UT","GP":3,"GS":0,"PA":2,"BA":0,"OBP":0.5,"SLG":0,"OPS":0.5,"AB":1,"R":0,"H":0,"1B":0,"2B":0,"3B":0,"TB":0,"HR":0,"RBI":0,"BB":1,"BB%":50,"HBP":0,"SF":0,"SH":0,"K":1,"K%":50,"DP":0,"CS":0,"SB":0,"ISO":0,"teamid":574333,"conference_id":"30183","player_id":"8528660","player_url":"http://stats.ncaa.org/players/8528660?year_stat_category_id=15080"},{"year":"2024","school":"Notre Dame (OH)","conference":"MEC","division":"2","Jersey":"26","Player":"Aaron Miranda","Yr":"Fr","Pos":"UT","GP":45,"GS":42,"PA":152,"BA":0.254,"OBP":0.355,"SLG":0.377,"OPS":0.732,"AB":130,"R":20,"H":33,"1B":24,"2B":5,"3B":1,"TB":49,"HR":3,"RBI":17,"BB":10,"BB%":6.6,"HBP":11,"SF":1,"SH":0,"K":34,"K%":22.4,"DP":2,"CS":2,"SB":4,"BABIP":0.319,"ISO":0.123,"teamid":574333,"conference_id":"30183","player_id":"8528664","player_url":"http://stats.ncaa.org/players/8528664?year_stat_category_id=15080"},{"year":"2024","school":"Notre Dame (OH)","conference":"MEC","division":"2","Jersey":"31","Player":"Noah Phillips","Yr":"Fr","Pos":"P","GP":4,"GS":0,"PA":1,"BA":0,"OBP":0,"SLG":0,"OPS":0,"AB":1,"R":0,"H":0,"1B":0,"2B":0,"3B":0,"TB":0,"HR":0,"RBI":0,"BB":0,"BB%":0,"HBP":0,"SF":0,"SH":0,"K":0,"K%":0,"DP":0,"CS":0,"SB":0,"BABIP":0,"ISO":0,"teamid":574333,"conference_id":"30183","player_id":"8528666","player_url":"http://stats.ncaa.org/players/8528666?year_stat_category_id=15080"},{"year":"2024","school":"Notre Dame (OH)","conference":"MEC","division":"2","Jersey":"24","Player":"Joe Prevesk","Yr":"Sr","Pos":"INF","GP":4,"GS":1,"PA":6,"BA":0,"OBP":0.167,"SLG":0,"OPS":0.167,"AB":5,"R":1,"H":0,"1B":0,"2B":0,"3B":0,"TB":0,"HR":0,"RBI":0,"BB":1,"BB%":16.7,"HBP":0,"SF":0,"SH":0,"K":3,"K%":50,"DP":0,"CS":0,"SB":0,"BABIP":0,"ISO":0,"teamid":574333,"conference_id":"30183","player_id":"8270589","player_url":"http://stats.ncaa.org/players/8270589?year_stat_category_id=15080"},{"year":"2024","school":"Notre Dame (OH)","conference":"MEC","division":"2","Jersey":"36","Player":"William Reaume","Yr":"So","Pos":"INF","GP":5,"GS":0,"PA":5,"BA":0,"OBP":0.4,"SLG":0,"OPS":0.4,"AB":3,"R":1,"H":0,"1B":0,"2B":0,"3B":0,"TB":0,"HR":0,"RBI":0,"BB":2,"BB%":40,"HBP":0,"SF":0,"SH":0,"K":2,"K%":40,"DP":0,"CS":0,"SB":0,"BABIP":0,"ISO":0,"teamid":574333,"conference_id":"30183","player_id":"8277076","player_url":"http://stats.ncaa.org/players/8277076?year_stat_category_id=15080"},{"year":"2024","school":"Notre Dame (OH)","conference":"MEC","division":"2","Jersey":"5","Player":"Tyler Shadle","Yr":"Sr","Pos":"C","GP":37,"GS":36,"PA":136,"BA":0.243,"OBP":0.326,"SLG":0.304,"OPS":0.63,"AB":115,"R":11,"H":28,"1B":23,"2B":4,"3B":0,"TB":35,"HR":1,"RBI":12,"BB":13,"BB%":9.6,"HBP":3,"SF":4,"SH":1,"K":14,"K%":10.3,"DP":6,"CS":0,"SB":0,"BABIP":0.26,"ISO":0.061,"teamid":574333,"conference_id":"30183","player_id":"8273316","player_url":"http://stats.ncaa.org/players/8273316?year_stat_category_id=15080"},{"year":"2024","school":"Notre Dame (OH)","conference":"MEC","division":"2","Jersey":"30","Player":"Damion Legaspe","Yr":"Sr","Pos":"INF","GP":32,"GS":24,"PA":86,"BA":0.25,"OBP":0.345,"SLG":0.333,"OPS":0.678,"AB":72,"R":13,"H":18,"1B":14,"2B":3,"3B":0,"TB":24,"HR":1,"RBI":6,"BB":10,"BB%":11.6,"HBP":1,"SF":1,"SH":2,"K":21,"K%":24.4,"DP":1,"CS":0,"SB":3,"BABIP":0.333,"ISO":0.083,"teamid":574333,"conference_id":"30183","player_id":"8265257","player_url":"http://stats.ncaa.org/players/8265257?year_stat_category_id=15080"},{"year":"2024","school":"Notre Dame (OH)","conference":"MEC","division":"2","Jersey":"29","Player":"Devon Minney","Yr":"So","Pos":"INF","GP":28,"GS":22,"PA":65,"BA":0.17,"OBP":0.279,"SLG":0.226,"OPS":0.505,"AB":53,"R":4,"H":9,"1B":8,"2B":0,"3B":0,"TB":12,"HR":1,"RBI":3,"BB":2,"BB%":3.1,"HBP":6,"SF":0,"SH":4,"K":10,"K%":15.4,"DP":2,"CS":1,"SB":0,"BABIP":0.19,"ISO":0.056,"teamid":574333,"conference_id":"30183","player_id":"8271111","player_url":"http://stats.ncaa.org/players/8271111?year_stat_category_id=15080"},{"year":"2024","school":"Notre Dame (OH)","conference":"MEC","division":"2","Jersey":"6","Player":"Jordan Long","Yr":"Jr","Pos":"INF","GP":11,"GS":3,"PA":20,"BA":0.158,"OBP":0.2,"SLG":0.211,"OPS":0.411,"AB":19,"R":3,"H":3,"1B":2,"2B":1,"3B":0,"TB":4,"HR":0,"RBI":1,"BB":1,"BB%":5,"HBP":0,"SF":0,"SH":0,"K":10,"K%":50,"DP":0,"CS":0,"SB":0,"BABIP":0.333,"ISO":0.053,"teamid":574333,"conference_id":"30183","player_id":"8279094","player_url":"http://stats.ncaa.org/players/8279094?year_stat_category_id=15080"},{"year":"2024","school":"Notre Dame (OH)","conference":"MEC","division":"2","Jersey":"10","Player":"Gabriel Miller","Yr":"Fr","Pos":"OF","GP":4,"GS":2,"PA":1,"BA":0,"OBP":0,"SLG":0,"OPS":0,"AB":1,"R":0,"H":0,"1B":0,"2B":0,"3B":0,"TB":0,"HR":0,"RBI":0,"BB":0,"BB%":0,"HBP":0,"SF":0,"SH":0,"K":1,"K%":100,"DP":0,"CS":0,"SB":0,"ISO":0,"teamid":574333,"conference_id":"30183","player_id":"8528648","player_url":"http://stats.ncaa.org/players/8528648?year_stat_category_id=15080"},{"year":"2024","school":"Notre Dame (OH)","conference":"MEC","division":"2","Jersey":"11","Player":"Andrew Eichenauer","Yr":"Fr","Pos":"INF","GP":10,"GS":4,"PA":18,"BA":0.077,"OBP":0.333,"SLG":0.077,"OPS":0.41,"AB":13,"R":3,"H":1,"1B":1,"2B":0,"3B":0,"TB":1,"HR":0,"RBI":0,"BB":4,"BB%":22.2,"HBP":1,"SF":0,"SH":0,"K":5,"K%":27.8,"DP":0,"CS":0,"SB":0,"BABIP":0.125,"ISO":0,"teamid":574333,"conference_id":"30183","player_id":"8528650","player_url":"http://stats.ncaa.org/players/8528650?year_stat_category_id=15080"},{"year":"2024","school":"Notre Dame (OH)","conference":"MEC","division":"2","Jersey":"15","Player":"Alexander Jones","Yr":"Jr","Pos":"OF","GP":49,"GS":47,"PA":176,"BA":0.333,"OBP":0.454,"SLG":0.413,"OPS":0.867,"AB":138,"R":23,"H":46,"1B":36,"2B":9,"3B":1,"TB":57,"HR":0,"RBI":25,"BB":22,"BB%":12.5,"HBP":11,"SF":3,"SH":2,"K":31,"K%":17.6,"DP":2,"CS":5,"SB":11,"BABIP":0.418,"ISO":0.08,"teamid":574333,"conference_id":"30183","player_id":"8528654","player_url":"http://stats.ncaa.org/players/8528654?year_stat_category_id=15080"},{"year":"2024","school":"Notre Dame (OH)","conference":"MEC","division":"2","Jersey":"23","Player":"Nolan James","Yr":"Fr","Pos":"INF","GP":5,"GS":5,"PA":18,"BA":0.176,"OBP":0.222,"SLG":0.176,"OPS":0.398,"AB":17,"R":1,"H":3,"1B":3,"2B":0,"3B":0,"TB":3,"HR":0,"RBI":1,"BB":1,"BB%":5.6,"HBP":0,"SF":0,"SH":0,"K":6,"K%":33.3,"DP":0,"CS":0,"SB":1,"BABIP":0.273,"ISO":0,"teamid":574333,"conference_id":"30183","player_id":"8528662","player_url":"http://stats.ncaa.org/players/8528662?year_stat_category_id=15080"},{"year":"2024","school":"Notre Dame (OH)","conference":"MEC","division":"2","Jersey":"32","Player":"Cadence Varner","Yr":"Fr","Pos":"OF","GP":13,"GS":11,"PA":40,"BA":0.152,"OBP":0.3,"SLG":0.333,"OPS":0.633,"AB":33,"R":7,"H":5,"1B":3,"2B":0,"3B":0,"TB":11,"HR":2,"RBI":3,"BB":6,"BB%":15,"HBP":1,"SF":0,"SH":0,"K":15,"K%":37.5,"DP":0,"CS":0,"SB":1,"BABIP":0.188,"ISO":0.181,"teamid":574333,"conference_id":"30183","player_id":"8528667","player_url":"http://stats.ncaa.org/players/8528667?year_stat_category_id=15080"},{"year":"2024","school":"Notre Dame (OH)","conference":"MEC","division":"2","Jersey":"34","Player":"Zachary Kakos","Yr":"So","Pos":"UT","GP":4,"GS":0,"PA":3,"BA":0.5,"OBP":0.667,"SLG":0.5,"OPS":1.167,"AB":2,"R":0,"H":1,"1B":1,"2B":0,"3B":0,"TB":1,"HR":0,"RBI":1,"BB":1,"BB%":33.3,"HBP":0,"SF":0,"SH":0,"K":1,"K%":33.3,"DP":0,"CS":0,"SB":0,"BABIP":1,"ISO":0,"teamid":574333,"conference_id":"30183","player_id":"8279234","player_url":"http://stats.ncaa.org/players/8279234?year_stat_category_id=15080"},{"year":"2024","school":"Notre Dame (OH)","conference":"MEC","division":"2","Jersey":"9","Player":"Caden Gomes","Yr":"Jr","Pos":"INF","GP":43,"GS":41,"PA":156,"BA":0.298,"OBP":0.41,"SLG":0.412,"OPS":0.822,"AB":131,"R":21,"H":39,"1B":26,"2B":12,"3B":0,"TB":54,"HR":1,"RBI":9,"BB":21,"BB%":13.5,"HBP":4,"SF":0,"SH":0,"K":21,"K%":13.5,"DP":1,"CS":0,"SB":3,"BABIP":0.349,"ISO":0.114,"teamid":574333,"conference_id":"30183","player_id":"8283169","player_url":"http://stats.ncaa.org/players/8283169?year_stat_category_id=15080"},{"year":"2024","school":"Notre Dame (OH)","conference":"MEC","division":"2","Jersey":"2","Player":"Johnny Costella","Yr":"Sr","Pos":"SS","GP":27,"GS":24,"PA":96,"BA":0.163,"OBP":0.292,"SLG":0.175,"OPS":0.467,"AB":80,"R":11,"H":13,"1B":12,"2B":1,"3B":0,"TB":14,"HR":0,"RBI":6,"BB":15,"BB%":15.6,"HBP":0,"SF":1,"SH":0,"K":20,"K%":20.8,"DP":4,"CS":0,"SB":0,"BABIP":0.213,"ISO":0.012,"teamid":574333,"conference_id":"30183","player_id":"8281373","player_url":"http://stats.ncaa.org/players/8281373?year_stat_category_id=15080"},{"year":"2024","school":"Notre Dame (OH)","conference":"MEC","division":"2","Jersey":"37","Player":"Nate Miller","Yr":"Jr","Pos":"C","GP":21,"GS":15,"PA":49,"BA":0.225,"OBP":0.347,"SLG":0.35,"OPS":0.697,"AB":40,"R":3,"H":9,"1B":6,"2B":2,"3B":0,"TB":14,"HR":1,"RBI":7,"BB":8,"BB%":16.3,"HBP":0,"SF":1,"SH":0,"K":12,"K%":24.5,"DP":0,"CS":0,"SB":3,"BABIP":0.286,"ISO":0.125,"teamid":574333,"conference_id":"30183","player_id":"8282652","player_url":"http://stats.ncaa.org/players/8282652?year_stat_category_id=15080"},{"year":"2024","school":"Notre Dame (OH)","conference":"MEC","division":"2","Jersey":"8","Player":"Jacob Barker","Yr":"Fr","Pos":"UT","GP":39,"GS":39,"PA":152,"BA":0.199,"OBP":0.276,"SLG":0.309,"OPS":0.585,"AB":136,"R":23,"H":27,"1B":16,"2B":8,"3B":2,"TB":42,"HR":1,"RBI":13,"BB":11,"BB%":7.2,"HBP":4,"SF":1,"SH":0,"K":32,"K%":21.1,"DP":7,"CS":0,"SB":3,"BABIP":0.25,"ISO":0.11,"teamid":574333,"conference_id":"30183","player_id":"8528644","player_url":"http://stats.ncaa.org/players/8528644?year_stat_category_id=15080"},{"year":"2024","school":"Notre Dame (OH)","conference":"MEC","division":"2","Jersey":"27","Player":"Hudson Wesney","Yr":"Fr","Pos":"UT","GP":26,"GS":15,"PA":43,"BA":0.128,"OBP":0.163,"SLG":0.205,"OPS":0.368,"AB":39,"R":6,"H":5,"1B":2,"2B":3,"3B":0,"TB":8,"HR":0,"RBI":4,"BB":1,"BB%":2.3,"HBP":1,"SF":2,"SH":0,"K":14,"K%":32.6,"DP":0,"CS":0,"SB":0,"BABIP":0.185,"ISO":0.077,"teamid":574333,"conference_id":"30183","player_id":"8528665","player_url":"http://stats.ncaa.org/players/8528665?year_stat_category_id=15080"},{"year":"2024","school":"Notre Dame (OH)","conference":"MEC","division":"2","Jersey":"33","Player":"Dylan Wimbs","Yr":"Fr","Pos":"OF","GP":30,"GS":22,"PA":81,"BA":0.231,"OBP":0.363,"SLG":0.369,"OPS":0.732,"AB":65,"R":7,"H":15,"1B":10,"2B":3,"3B":0,"TB":24,"HR":2,"RBI":13,"BB":7,"BB%":8.6,"HBP":7,"SF":1,"SH":1,"K":22,"K%":27.2,"DP":1,"CS":1,"SB":1,"BABIP":0.31,"ISO":0.138,"teamid":574333,"conference_id":"30183","player_id":"8528668","player_url":"http://stats.ncaa.org/players/8528668?year_stat_category_id=15080"}]
